Workbook

Sheet Supuestos
A1: Wabee - Supuestos del modelo
A2: Edita las celdas amarillas (azul=entrada). Tarifas Meta WhatsApp Mexico 2025. Moneda: MXN.
A4: Parametro | B4: Valor | C4: Nota
A5: Tipo de cambio USD a MXN | B5: 18 | C5: Banxico ~17.80 jun-2026; 18 conservador
A6: Meta - Servicio (USD/conv) | B6: 0 | C6: Conversaciones iniciadas por el cliente: gratis
A7: Meta - Utilidad (USD/plantilla) | B7: 0.008 | C7: Utility template
A8: Meta - Marketing (USD/plantilla) | B8: 0.029 | C8: Marketing template
A9: Meta - Autenticacion (USD/plantilla) | B9: 0.0135 | C9: Auth template
A10: Gemini IA (USD/conversacion) | B10: 0.001 | C10: ~ 0.30 USD por 300 conversaciones
A11: Correo (USD/cuenta/mes) | B11: 0.05 | C11: Invitaciones, verificacion, notificaciones
A12: Costo fijo prorrateado (USD/cuenta/mes) | B12: 20 | C12: Infraestructura fija / nro de cuentas activas

Sheet Costo por perfil
A1: Costo real de servir a un usuario
A2: Itemizado por perfil. Formulas en MXN enlazadas a Supuestos.
A4: Concepto | B4: Ligero | C4: Medio | D4: Pesado (con campana) | E4: Pesado sin campana
A5: Conversaciones totales | B5: 300 | C5: 1500 | D5: 6000 | E5: 6000
A6: Entrantes (cliente inicia) - gratis | B6: 240 | C6: 1050 | D6: 4000 | E6: 4000
A7: Plantillas Utilidad | B7: 60 | C7: 300 | D7: 2000 | E7: 2000
A8: Plantillas Marketing | B8: 0 | C8: 150 | D8: 5000 | E8: 0
A9: Plantillas Autenticacion | B9: 0 | C9: 0 | D9: 0 | E9: 0
A10: Conversaciones con IA (Gemini) | B10: 300 | C10: 1500 | D10: 6000 | E10: 6000
A11: Costo WhatsApp (MXN) | B11: =(B7*Supuestos!$B$7+B8*Supuestos!$B$8+B9*Supuestos!$B$9)*Supuestos!$B$5 -> 8.64 | C11: =(C7*Supuestos!$B$7+C8*Supuestos!$B$8+C9*Supuestos!$B$9)*Supuestos!$B$5 -> 121.5 | D11: =(D7*Supuestos!$B$7+D8*Supuestos!$B$8+D9*Supuestos!$B$9)*Supuestos!$B$5 -> 2898 | E11: =(E7*Supuestos!$B$7+E8*Supuestos!$B$8+E9*Supuestos!$B$9)*Supuestos!$B$5 -> 288
A12: Costo IA Gemini (MXN) | B12: =(B10*Supuestos!$B$10)*Supuestos!$B$5 -> 5.4 | C12: =(C10*Supuestos!$B$10)*Supuestos!$B$5 -> 27 | D12: =(D10*Supuestos!$B$10)*Supuestos!$B$5 -> 108 | E12: =(E10*Supuestos!$B$10)*Supuestos!$B$5 -> 108
A13: Costo correo (MXN) | B13: =Supuestos!$B$11*Supuestos!$B$5 -> 0.9 | C13: =Supuestos!$B$11*Supuestos!$B$5 -> 0.9 | D13: =Supuestos!$B$11*Supuestos!$B$5 -> 0.9 | E13: =Supuestos!$B$11*Supuestos!$B$5 -> 0.9
A14: Costo VARIABLE / usuario (MXN) | B14: =B11+B12+B13 -> 14.94 | C14: =C11+C12+C13 -> 149.4 | D14: =D11+D12+D13 -> 3006.9 | E14: =E11+E12+E13 -> 396.9
A15: Costo fijo prorrateado (MXN) | B15: =Supuestos!$B$12*Supuestos!$B$5 -> 360 | C15: =Supuestos!$B$12*Supuestos!$B$5 -> 360 | D15: =Supuestos!$B$12*Supuestos!$B$5 -> 360 | E15: =Supuestos!$B$12*Supuestos!$B$5 -> 360
A16: COSTO TOTAL de servir (MXN) | B16: =B14+B15 -> 374.94 | C16: =C14+C15 -> 509.4 | D16: =D14+D15 -> 3366.9 | E16: =E14+E15 -> 756.9
A18: Nota: 'Pesado con campana' incluye 5,000 plantillas de marketing que el CLIENTE paga via excedente. El costo del plan Business usa 'Pesado sin campana'.

Sheet Planes
A1: Wabee - Planes y precios (MXN / mes)
A2: Free + 3 planes de pago. Cupo de plantillas + excedente. Facturacion mensual.
A4: Caracteristica | B4: Free (prueba) | C4: Starter | D4: Pro | E4: Business | F4: Notas / dimension
A5: Precio MXN / mes | B5: 0 | C5: 749 | D5: 1799 | E5: 4499 | F5: Mensual, sin IVA
A6: Canales WhatsApp | B6: 1 | C6: 1 | D6: 3 | E6: 10 | F6: countChannels
A7: Contactos | B7: 50 | C7: 1000 | D7: 5000 | E7: 25000 | F7: countContacts
A8: Agentes IA (perfiles) | B8: 1 | C8: 2 | D8: 5 | E8: Ilimitados | F8: countAiAgents
A9: Automatizaciones (flujos) | B9: 1 | C9: 5 | D9: 25 | E9: Ilimitadas
A10: Campanas / mes | B10: - | C10: 2 | D10: 10 | E10: Ilimitadas | F10: countCampaignsThisMonth
A11: Miembros del equipo | B11: 1 | C11: 3 | D11: 10 | E11: 25 | F11: countTeamMembers
A12: Plantillas incluidas / mes | B12: 1 (demo) | C12: 100 | D12: 500 | E12: 2000 | F12: FALTA EN MODELO - agregar
A13: Excedente por plantilla (MXN) | B13: - | C13: 0.95 | D13: 0.75 | E13: 0.55 | F13: FALTA EN MODELO - agregar
A14: Mensajes de IA / mes | B14: 10 (demo) | C14: 1000 | D14: 5000 | E14: 20000 | F14: FALTA EN MODELO - agregar
A15: Entrenamiento de IA (fuentes) | B15: 1 (demo) | C15: 3 | D15: 10 | E15: Ilimitado | F15: para ver como funciona
A16: Storage media | B16: 200 MB | C16: 5 GB | D16: 20 GB | E16: 100 GB | F16: limite STORAGE
A17: Widgets web | B17: 1 | C17: 1 | D17: 3 | E17: 10
A18: Marketplace de plantillas | B18: Ver | C18: Instalar | D18: Instalar + publicar | E18: Completo | F18: marketplace_access
A19: Integraciones CRM | B19: - | C19: - | D19: Si | E19: Si | F19: crm_integrations
A20: Soporte | B20: Comunidad | C20: Email | D20: Email prioritario | E20: Prioritario + onboarding

Sheet Margenes
A1: Precio vs costo y margen por plan
A2: Costo de servir enlazado a 'Costo por perfil'. Margen sin excedentes.
A4: Plan | B4: Precio (MXN) | C4: Costo de servir (MXN) | D4: Margen bruto (MXN) | E4: Margen %
A5: Free (prueba) | B5: =Planes!$B$5 -> 0 | C5: ='Costo por perfil'!$B$16 -> 374.94 | D5: =B5-C5 -> -374.94 | E5: =IF(B5=0,0,D5/B5) -> 0
A6: Starter | B6: =Planes!$C$5 -> 749 | C6: ='Costo por perfil'!$B$16 -> 374.94 | D6: =B6-C6 -> 374.06 | E6: =IF(B6=0,0,D6/B6) -> 0.49941255
A7: Pro | B7: =Planes!$D$5 -> 1799 | C7: ='Costo por perfil'!$C$16 -> 509.4 | D7: =B7-C7 -> 1289.6 | E7: =IF(B7=0,0,D7/B7) -> 0.71684269
A8: Business | B8: =Planes!$E$5 -> 4499 | C8: ='Costo por perfil'!$E$16 -> 756.9 | D8: =B8-C8 -> 3742.1 | E8: =IF(B8=0,0,D8/B8) -> 0.83176261
A10: El plan Free tiene margen negativo (costo de adquisicion); se recupera al convertir a planes de pago.

Sheet Simulador excedentes
A1: Simulador de excedentes de plantillas
A2: Demuestra: la campana la paga el cliente. Edita celdas amarillas.
A4: Entrada | B4: Valor | C4: Nota
A5: Plantillas incluidas en el plan | B5: 2000 | C5: Ej. Business = 2,000
A6: Precio de excedente (MXN/plantilla) | B6: 0.55 | C6: Ej. Business = 0.55
A7: Plantillas Marketing enviadas | B7: 5000 | C7: Campana masiva
A8: Plantillas Utilidad enviadas | B8: 0
A10: Resultado | B10: MXN | C10: Formula
A11: Total plantillas enviadas | B11: =B7+B8 -> 5000 | C11: mkt + utilidad
A12: Plantillas en excedente | B12: =MAX(0,B11-B5) -> 3000 | C12: enviadas menos incluidas
A13: Costo Meta TOTAL de la campana (MXN) | B13: =(B7*Supuestos!$B$8+B8*Supuestos!$B$7)*Supuestos!$B$5 -> 2610 | C13: informativo
A14: Costo Meta del EXCEDENTE (marginal, MXN) | B14: =IF(B11=0,0,B12*B13/B11) -> 1566 | C14: excedente x costo Meta promedio
A15: Cobro al cliente por excedente (MXN) | B15: =B12*B6 -> 1650 | C15: excedente x precio
A16: Ganancia NETA del excedente (MXN) | B16: =B15-B14 -> 84 | C16: cobro menos costo Meta del excedente
A18: Las plantillas INCLUIDAS las absorbe el precio del plan (por eso Business tiene ~80% de margen). El EXCEDENTE se cobra por encima de su costo Meta marginal, asi una campana grande deja margen.
A19: Importante: manten el precio de excedente por encima de la tarifa de marketing (~0.52 MXN/plantilla) para no perder en campanas 100% marketing.

Sheet Competencia
A1: Comparativa de precios - competencia (jun 2026)
A2: Referencia USD y equivalente MXN. Posicionamiento, no copia.
A4: Plataforma | B4: Rango de planes | C4: Desde USD | D4: Hasta USD | E4: Modelo de cobro
A5: Respond.io | B5: Starter-Advanced | C5: 79 | D5: 279 | E5: Por contactos activos (MAC) + mensajes aparte
A6: Wati | B6: Growth-Business | C6: 59 | D6: 279 | E6: Suscripcion + mensajes +20% Meta + add-ons
A7: ManyChat | B7: Free-Business | C7: 0 | D7: 69 | E7: Por contactos + add-on IA 29 USD + fees WhatsApp
A8: Cliengo | B8: Starter-Corporate | C8: 24 | D8: 300 | E8: Por conversaciones/agentes + WhatsApp API
A10: Wabee | B10: Free-Business (MXN) | C10: =Planes!C5/Supuestos!$B$5 -> 41.611111 | D10: =Planes!E5/Supuestos!$B$5 -> 249.94444 | E10: Cupo de plantillas + excedente (campana la paga el cliente)
A11: Wabee precio MXN | C11: =Planes!C5 -> 749 | D11: =Planes!E5 -> 4499 | E11: 749 / 1,799 / 4,499 MXN (Starter/Pro/Business)
